phonepe/__init__.py
phonepe/sdk/__init__.py
phonepe/sdk/pg/__init__.py
phonepe/sdk/pg/env.py
phonepe/sdk/pg/common/__init__.py
phonepe/sdk/pg/common/base_client.py
phonepe/sdk/pg/common/exceptions.py
phonepe/sdk/pg/common/configs/__init__.py
phonepe/sdk/pg/common/configs/credential_config.py
phonepe/sdk/pg/common/constants/__init__.py
phonepe/sdk/pg/common/constants/base_urls.py
phonepe/sdk/pg/common/constants/headers.py
phonepe/sdk/pg/common/events/__init__.py
phonepe/sdk/pg/common/events/constants.py
phonepe/sdk/pg/common/events/event_builder.py
phonepe/sdk/pg/common/events/event_queue_handler.py
phonepe/sdk/pg/common/events/models/__init__.py
phonepe/sdk/pg/common/events/models/base_event.py
phonepe/sdk/pg/common/events/models/bulk_event.py
phonepe/sdk/pg/common/events/models/event_data.py
phonepe/sdk/pg/common/events/models/enums/__init__.py
phonepe/sdk/pg/common/events/models/enums/event_state.py
phonepe/sdk/pg/common/events/models/enums/event_type.py
phonepe/sdk/pg/common/events/models/enums/flow_type.py
phonepe/sdk/pg/common/events/publisher/__init__.py
phonepe/sdk/pg/common/events/publisher/event_publisher.py
phonepe/sdk/pg/common/events/publisher/event_publisher_factory.py
phonepe/sdk/pg/common/events/publisher/queued_event_publisher.py
phonepe/sdk/pg/common/http_client_modules/__init__.py
phonepe/sdk/pg/common/http_client_modules/base_http_command.py
phonepe/sdk/pg/common/http_client_modules/http_method_type.py
phonepe/sdk/pg/common/http_client_modules/phonepe_response.py
phonepe/sdk/pg/common/models/__init__.py
phonepe/sdk/pg/common/models/payment_flow_type.py
phonepe/sdk/pg/common/models/request/__init__.py
phonepe/sdk/pg/common/models/request/account_constraint.py
phonepe/sdk/pg/common/models/request/device_context.py
phonepe/sdk/pg/common/models/request/instrument_constraint.py
phonepe/sdk/pg/common/models/request/meta_info.py
phonepe/sdk/pg/common/models/request/payment_flow.py
phonepe/sdk/pg/common/models/request/pg_payment_request.py
phonepe_pg_sdk_python-2.1.6.dist-info/licenses/LICENSE
phonepe_pg_sdk_python-2.1.6.dist-info/METADATA
phonepe_pg_sdk_python-2.1.6.dist-info/WHEEL
phonepe_pg_sdk_python-2.1.6.dist-info/top_level.txt
phonepe_pg_sdk_python-2.1.6.dist-info/RECORD
