Metadata-Version: 2.4
Name: phonepe-pg-sdk-python
Version: 2.1.6
Summary: SDK for integration with PhonePe PG APIs
Author: PhonePe
License-File: LICENSE
Requires-Dist: APScheduler<=3.10.1
Requires-Dist: dataclasses-json<=0.5.8
Requires-Dist: requests<=2.31.0
Requires-Dist: urllib3<=1.26.12
Dynamic: author
Dynamic: license-file
Dynamic: requires-dist
Dynamic: summary
